Preln/__init__.py
Preln/preprocessing.py
Preln/stopwords.py
Preln/_external/corpus.txt
Preln/_external/stopwords.csv
Preln/core/__init__.py
Preln/core/accents.py
Preln/core/autocorrect.py
Preln/core/date.py
Preln/core/lowercasing.py
Preln/core/media.py
Preln/core/numbers.py
Preln/core/privacy.py
Preln/core/punctuation.py
Preln/core/stopwords.py
Preln/core/tokenizer.py
Preln/core/__features/__init__.py
Preln/core/__features/lev_distance.py
preln-0.5.5.dist-info/LICENSE
preln-0.5.5.dist-info/METADATA
preln-0.5.5.dist-info/WHEEL
preln-0.5.5.dist-info/top_level.txt
preln-0.5.5.dist-info/RECORD
