Metadata-Version: 2.1
Name: preln
Version: 0.5.5
Summary: A preprocessing libray for text in spanish
Home-page: https://github.com/Adri-Hdez/Preln
Author: Adrián H.S & Raúl M.R
Author-email: adrihs.dev@gmail.com
License: MIT
License-File: LICENSE
Requires-Dist: pandas
Requires-Dist: nltk
Requires-Dist: numpy
Requires-Dist: openpyxl
Requires-Dist: lxml
Requires-Dist: sqlalchemy
Requires-Dist: es-core-news-sm
